icx360/__init__.py
icx360/algorithms/__init__.py
icx360/algorithms/lbbe.py
icx360/algorithms/lwbe.py
icx360/algorithms/cell/CELL.py
icx360/algorithms/cell/__init__.py
icx360/algorithms/cell/mCELL.py
icx360/algorithms/mexgen/__init__.py
icx360/algorithms/mexgen/clime.py
icx360/algorithms/mexgen/lshap.py
icx360/algorithms/mexgen/mexgen.py
icx360/algorithms/token_highlighter/__init__.py
icx360/algorithms/token_highlighter/th_llm.py
icx360/metrics/__init__.py
icx360/metrics/perturb_curve.py
icx360/utils/__init__.py
icx360/utils/coloring_utils.py
icx360/utils/general_utils.py
icx360/utils/subset_utils.py
icx360/utils/toma.py
icx360/utils/infillers/BART_infiller.py
icx360/utils/infillers/T5_infiller.py
icx360/utils/infillers/__init__.py
icx360/utils/model_wrappers/__init__.py
icx360/utils/model_wrappers/base_model_wrapper.py
icx360/utils/model_wrappers/huggingface.py
icx360/utils/model_wrappers/vllm.py
icx360/utils/scalarizers/__init__.py
icx360/utils/scalarizers/bart_score.py
icx360/utils/scalarizers/base_scalarizer.py
icx360/utils/scalarizers/bleu_scalarizer.py
icx360/utils/scalarizers/contradiction_scalarizer.py
icx360/utils/scalarizers/nli_scalarizer.py
icx360/utils/scalarizers/preference_scalarizer.py
icx360/utils/scalarizers/prob.py
icx360/utils/scalarizers/text_only.py
icx360/utils/segmenters/__init__.py
icx360/utils/segmenters/spacy.py
icx360/utils/segmenters/utils.py
icx360-0.1.0.dist-info/licenses/LICENSE
tests/conftest.py
tests/integration/test_cell_nlg.py
tests/integration/test_mexgen_question_answering.py
tests/integration/test_mexgen_rag.py
tests/integration/test_mexgen_summarization.py
tests/integration/test_token_highlighter.py
tests/unit/test_bleu_scalarized_model.py
tests/unit/test_contradiction_scalarized_model.py
tests/unit/test_huggingface.py
tests/unit/test_infiller_bart.py
tests/unit/test_infiller_t5.py
tests/unit/test_nli_scalarized_model.py
tests/unit/test_preference_scalarized_model.py
tests/unit/test_prob_scalarized_model.py
tests/unit/test_segmenter.py
icx360-0.1.0.dist-info/METADATA
icx360-0.1.0.dist-info/WHEEL
icx360-0.1.0.dist-info/top_level.txt
icx360-0.1.0.dist-info/RECORD
