Metadata-Version: 2.4
Name: icx360
Version: 0.1.0
Summary: In-Context Explainability 360 Toolkit
Author: IBM Research
Maintainer-email: ibm <ibm@ibm.com>
License: Apache-2.0
Requires-Python: <3.13,>=3.11
License-File: LICENSE
Requires-Dist: numpy
Requires-Dist: transformers
Requires-Dist: torch>=2.0
Requires-Dist: jupyterlab
Requires-Dist: notebook
Requires-Dist: evaluate
Requires-Dist: bert_score
Requires-Dist: nltk
Requires-Dist: sentencepiece
Requires-Dist: protobuf
Requires-Dist: toma
Requires-Dist: sentence-transformers
Requires-Dist: spacy
Requires-Dist: pytest
Requires-Dist: python-dotenv<2.0.0,>=1.1.0
Requires-Dist: openai<2.0.0,>=1.86.0
Requires-Dist: datasets<4.0.0
Requires-Dist: accelerate
Requires-Dist: pre-commit
Provides-Extra: docs
Requires-Dist: mkdocs-material; extra == "docs"
Requires-Dist: mkdocs-jupyter; extra == "docs"
Requires-Dist: mkdocs-click; extra == "docs"
Requires-Dist: mkdocs-include; extra == "docs"
Requires-Dist: mkdocstrings[python]; extra == "docs"
Requires-Dist: griffe_inherited_docstrings; extra == "docs"
Requires-Dist: griffe-pydantic; extra == "docs"
Requires-Dist: mkdocs-awesome-nav; extra == "docs"
Requires-Dist: mkdocs-include-markdown-plugin; extra == "docs"
Dynamic: license-file
